{
  "file_id": "c91ad5b1-aacf-4699-bda2-b671e888db70",
  "agent_name": "character_relationship_analyzer_agent",
  "output_tag": "character_development",
  "user_id": "default_user",
  "session_id": null,
  "timestamp": "2026-02-13T21:28:37.086840",
  "file_type": "json",
  "custom_metadata": {},
  "tag_info": {
    "name": "角色开发",
    "description": "角色开发相关的输出内容",
    "agents": [
      "character_profile_agent",
      "character_relationship_agent",
      "character_profile_generator_agent"
    ]
  }
}